mgenerator/__init__.py
mgenerator/generator.py
mgenerator-0.1.2.dist-info/LICENSE
mgenerator-0.1.2.dist-info/METADATA
mgenerator-0.1.2.dist-info/WHEEL
mgenerator-0.1.2.dist-info/top_level.txt
mgenerator-0.1.2.dist-info/RECORD
