Metadata-Version: 2.1
Name: mgenerator
Version: 0.1.2
Summary: Generate a sympy matrix fast
Home-page: https://github.com/echo724/matrix-generator.git
Author: Eunchan Cho
Author-email: eunchan1001@gmail.com
License: MIT
Platform: UNKNOWN
Classifier: License :: OSI Approved :: MIT License
Classifier: Operating System :: OS Independent
Classifier: Programming Language :: Python :: 3.7
Requires-Dist: sympy (>=1.6.1)
